{
  "cmd": "SUPER_CHAT_MESSAGE",
  "data": {
    "background_bottom_color": "#2A60B2",
    "background_color": "#EDF5FF",
    "background_color_end": "#405D85",
    "background_color_start": "#3171D2",
    "background_icon": "",
    "background_image": "https://i0.hdslb.com/bfs/live/a712efa5c6ebc67bafbe8352d3e74b820a00c13e.png",
    "background_price_color": "#7497CD",
    "color_point": 0.7,
    "dmscore": 72,
    "end_time": 1661528683,
    "gift": {
      "gift_id": 12000,
      "gift_name": "醒目留言",
      "num": 1
    },
    "id": 4898587,
    "is_ranked": 1,
    "is_send_audit": 0,
    "medal_info": {
      "anchor_roomid": 77777777773,
      "anchor_uname": "__MOCK_BADGE_ANCHOR_UNAME__",
      "guard_level": 0,
      "icon_id": 0,
      "is_lighted": 1,
      "medal_color": "#be6686",
      "medal_color_border": 12478086,
      "medal_color_end": 12478086,
      "medal_color_start": 12478086,
      "medal_level": 16,
      "medal_name": "__MOCK_BADGE_NAME__",
      "special": "",
      "target_id": 77777777772
    },
    "message": "__MOCK_MESSAGE_CONTENT__",
    "message_font_color": "#A3F6FF",
    "message_trans": "",
    "price": 30,
    "rate": 1000,
    "start_time": 1661528623,
    "time": 60,
    "token": "A1EC2662",
    "trans_mark": 0,
    "ts": 1661528623,
    "uid": 77777777771,
    "user_info": {
      "face": "http://__MOCK_FACE__.jpg",
      "face_frame": "",
      "guard_level": 0,
      "is_main_vip": 1,
      "is_svip": 0,
      "is_vip": 0,
      "level_color": "#61c05a",
      "manager": 0,
      "name_color": "#666666",
      "title": "title-111-1",
      "uname": "__MOCK_UNAME__",
      "user_level": 20
    }
  },
  "roomid": 77777777773
}